Metadata-Version: 1.0
Name: pulseaudio-switch
Version: 0.0.4
Summary: pulseaudio_switch
Home-page: https://github.com/eayin2/pulseaudio_switch
Author: eayin2
Author-email: eayin2@gmail.com
License: UNKNOWN
Platform: UNKNOWN
